pdstoolbox/__init__.py
pdstoolbox/pdstoolbox.py
pdstoolbox-0.0.5.dist-info/LICENSE
pdstoolbox-0.0.5.dist-info/METADATA
pdstoolbox-0.0.5.dist-info/WHEEL
pdstoolbox-0.0.5.dist-info/top_level.txt
pdstoolbox-0.0.5.dist-info/RECORD
